odoo/addons/event_email_reminder/README.rst
odoo/addons/event_email_reminder/__init__.py
odoo/addons/event_email_reminder/__manifest__.py
odoo/addons/event_email_reminder/data/event_stage_data.xml
odoo/addons/event_email_reminder/data/ir_cron_data.xml
odoo/addons/event_email_reminder/data/mail_template_data.xml
odoo/addons/event_email_reminder/i18n/es.po
odoo/addons/event_email_reminder/i18n/event_email_reminder.pot
odoo/addons/event_email_reminder/i18n/it.po
odoo/addons/event_email_reminder/models/__init__.py
odoo/addons/event_email_reminder/models/event_event.py
odoo/addons/event_email_reminder/models/event_stage.py
odoo/addons/event_email_reminder/readme/CONFIGURE.md
odoo/addons/event_email_reminder/readme/CONTRIBUTORS.md
odoo/addons/event_email_reminder/readme/CREDITS.md
odoo/addons/event_email_reminder/readme/DESCRIPTION.md
odoo/addons/event_email_reminder/static/description/icon.png
odoo/addons/event_email_reminder/static/description/index.html
odoo/addons/event_email_reminder/tests/__init__.py
odoo/addons/event_email_reminder/tests/test_event_event.py
odoo/addons/event_email_reminder/views/event_stage_views.xml
odoo_addon_event_email_reminder-17.0.1.0.0.2.dist-info/METADATA
odoo_addon_event_email_reminder-17.0.1.0.0.2.dist-info/WHEEL
odoo_addon_event_email_reminder-17.0.1.0.0.2.dist-info/top_level.txt
odoo_addon_event_email_reminder-17.0.1.0.0.2.dist-info/RECORD
